ez_setup.py
setup.py
wsgize/__init__.py
wsgize.egg-info/PKG-INFO
wsgize.egg-info/SOURCES.txt
wsgize.egg-info/dependency_links.txt
wsgize.egg-info/top_level.txt
wsgize.egg-info/zip-safe
wsgize/tests/__init__.py
wsgize/tests/test_wsgize.py
