Metadata-Version: 1.0
Name: wsgize
Version: 0.4
Summary: WSGI without the WSGI
Home-page: UNKNOWN
Author: L. C. Rees
Author-email: lcrees@gmail.com
License: BSD
Keywords: WSGI dispatch middleware web HTTP decorators
Platform: UNKNOWN
Classifier: Development Status :: 4 - Beta
Classifier: Environment :: Web Environment
Classifier: Intended Audience :: Developers
Classifier: License :: OSI Approved :: BSD License
Classifier: Natural Language :: English
Classifier: Operating System :: OS Independent
Classifier: Programming Language :: Python
Classifier: Topic :: Internet :: WWW/HTTP
Classifier: Topic :: Internet :: WWW/HTTP :: Dynamic Content
Classifier: Topic :: Internet :: WWW/HTTP :: WSGI
Classifier: Topic :: Internet :: WWW/HTTP :: WSGI :: Middleware
